{
  "author": "Thanh Hà",
  "copyright": null,
  "date_published": "2025-07-24T10:35:01+07:00",
  "date_modified": "2025-07-24T10:35:01+07:00",
  "language": "vi",
  "source": "nld",
  "title": "Sản lượng khí đốt Nga lao dốc, Trung Quốc không đủ bù đắp thị trường châu Âu",
  "description": " Sản lượng khí đốt Nga giảm bất chấp tăng xuất khẩu sang Trung Quốc và nhu cầu tiêu thụ trong nước tăng. ",
  "paragraphs": "Sản lượng khí đốt của Nga giảm 3,2% trong nửa đầu năm 2025, đạt 334,8 tỉ m3, khi xuất khẩu sang Trung Quốc tăng và nhu cầu trong nước tăng cũng không thể bù đắp cho lượng sụt giảm của dòng khí đốt Nga vận chuyển bằng đường ống sang châu Âu. Sự sụt giảm khí đốt Nga phản ánh tác động mang tính cấu trúc của quyết định hồi tháng 1 của Ukraina về việc chấm dứt thỏa thuận trung chuyển khí đốt Nga sang E U. Tuyến đường ống dẫn khí qua Ukraina vận chuyển hơn 15 tỉ m3 khí đốt riêng trong năm 2024, là hành lang quan trọng đưa khí đốt Nga sang E U. Hiện tại, Nga chỉ còn vận chuyển khí đốt sang E U thông qua Turk Stream. Lượng khí đốt Nga xuất qua Turk Stream và từ đó đưa sang Slovakia đã tăng lên nhưng chưa đủ",
  "url": "https://laodong.vn/the-gioi/san-luong-khi-dot-nga-lao-doc-trung-quoc-khong-du-bu-dap-thi-truong-chau-au-1545832.ldo",
  "image": "https://media-cdn-v2.laodong.vn/storage/newsportal/2025/7/24/1545832/Khi-Dot-Nga.jpg?w=800&h=420&crop=auto&scale=both",
  "label": 3,
  "type": "article"
}